yhttp/dev/__init__.py
yhttp/dev/fixtures.py
yhttp_dev-3.2.4.dist-info/LICENSE
yhttp_dev-3.2.4.dist-info/METADATA
yhttp_dev-3.2.4.dist-info/WHEEL
yhttp_dev-3.2.4.dist-info/top_level.txt
yhttp_dev-3.2.4.dist-info/RECORD
