Metadata-Version: 2.1
Name: yhttp-dev
Version: 3.2.4
Summary: yhttp development utilities
Home-page: https://github.com/yhttp/yhttp-dev
Author: pylover
Author-email: vahid.mardani@gmail.com
License-File: LICENSE
